poorconn/__init__.py
poorconn/__main__.py
poorconn/_accept.py
poorconn/_cli.py
poorconn/_send.py
poorconn/_socket.py
poorconn/_version.py
poorconn/_wrappers.py
poorconn/pytest_plugin/__init__.py
poorconn/pytest_plugin/_impl.py
poorconn-0.2.1.data/data/COPYING
poorconn-0.2.1.data/data/COPYING.GPL
poorconn-0.2.1.dist-info/COPYING
poorconn-0.2.1.dist-info/COPYING.GPL
poorconn-0.2.1.dist-info/METADATA
poorconn-0.2.1.dist-info/WHEEL
poorconn-0.2.1.dist-info/entry_points.txt
poorconn-0.2.1.dist-info/top_level.txt
poorconn-0.2.1.dist-info/RECORD
