Metadata-Version: 2.1
Name: poorconn
Version: 0.2.1
Summary: Simulating poor network connections.
Home-page: https://poorconn.topbug.net
Author: Hong Xu
Author-email: hong@topbug.net
License: LGPLv3+
Project-URL: Source, https://gitlab.com/xuhdev/poorconn
Project-URL: Tracker, https://gitlab.com/xuhdev/poorconn/issues
Keywords: socket,test,unittest
Platform: UNKNOWN
Classifier: Framework :: Pytest
Classifier: Intended Audience :: Developers
Classifier: License :: DFSG approved
Classifier: License :: OSI Approved :: GNU Lesser General Public License v3 or later (LGPLv3+)
Classifier: Operating System :: OS Independent
Classifier: Programming Language :: Python :: 3 :: Only
Classifier: Programming Language :: Python :: 3
Classifier: Programming Language :: Python :: 3.7
Classifier: Programming Language :: Python :: 3.8
Classifier: Programming Language :: Python :: 3.9
Classifier: Programming Language :: Python :: Implementation :: CPython
Classifier: Programming Language :: Python :: Implementation :: PyPy
Classifier: Programming Language :: Python
Classifier: Topic :: Software Development :: Libraries
Classifier: Topic :: Software Development :: Testing
Classifier: Topic :: Utilities
Requires-Python: >=3.7
Provides-Extra: full
Requires-Dist: pytest (>=6.2) ; extra == 'full'
